soundcraft/__init__.py
soundcraft/cli.py
soundcraft/dbus.py
soundcraft/gui.py
soundcraft/notepad.py
soundcraft/data/dbus-1/system-services/soundcraft.utils.notepad.service
soundcraft/data/dbus-1/system.d/soundcraft-utils.conf
soundcraft/data/xdg/soundcraft-utils.desktop
soundcraft/data/xdg/soundcraft-utils.png
soundcraft/data/xdg/soundcraft-utils.svg
soundcraft_utils-0.4.0.dist-info/LICENSE
soundcraft_utils-0.4.0.dist-info/METADATA
soundcraft_utils-0.4.0.dist-info/WHEEL
soundcraft_utils-0.4.0.dist-info/entry_points.txt
soundcraft_utils-0.4.0.dist-info/top_level.txt
soundcraft_utils-0.4.0.dist-info/RECORD
