Metadata-Version: 2.1
Name: soundcraft-utils
Version: 0.4.0
Summary: Soundcraft Notepad control utilities
Home-page: https://github.com/lack/soundcraft-utils
Author: Jim Ramsay
Author-email: i.am@jimramsay.com
License: MIT
Platform: UNKNOWN
Classifier: Programming Language :: Python :: 3
Classifier: License :: OSI Approved :: MIT License
Classifier: Operating System :: OS Independent
Classifier: Topic :: Multimedia :: Sound/Audio :: Mixers
Requires-Python: >=3.6
Requires-Dist: pyusb
Requires-Dist: pydbus
